OpenAnnotatePy/OpenAnnotateApi.py
OpenAnnotatePy/__init__.py
OpenAnnotatePy/__version__.py
OpenAnnotatePy-0.1.0.dist-info/METADATA
OpenAnnotatePy-0.1.0.dist-info/WHEEL
OpenAnnotatePy-0.1.0.dist-info/top_level.txt
OpenAnnotatePy-0.1.0.dist-info/RECORD
