Metadata-Version: 2.1
Name: OpenAnnotatePy
Version: 0.1.0
Summary: A python package for efficiently annotating the chromatin accessibility of genomic regions.
Home-page: https://github.com/ZjGaothu/OpenAnnotatePy
Author: Gaozj
Author-email: 3193346402@qq.com
License: Apache License 2.0
Project-URL: Web, http://health.tsinghua.edu.cn/openannotate
